promptory/__init__.py
promptory-0.0.0.dist-info/LICENSE
promptory-0.0.0.dist-info/METADATA
promptory-0.0.0.dist-info/WHEEL
promptory-0.0.0.dist-info/top_level.txt
promptory-0.0.0.dist-info/RECORD
